scola/__init__.py
scola/_common.py
scola/_compute_null_correlation_matrix.py
scola/_golden_section_search.py
scola/_iscola.py
scola/_scola.py
scola/corr2net.py
scola/generate_network.py
scola/gradient_descent.py
scola/null_models.py
scola/search_algorithm.py
scola-0.1.0.dist-info/DESCRIPTION.rst
scola-0.1.0.dist-info/METADATA
scola-0.1.0.dist-info/RECORD
scola-0.1.0.dist-info/WHEEL
scola-0.1.0.dist-info/metadata.json
scola-0.1.0.dist-info/top_level.txt
